setup.py
cernest_probability/Binomialdistribution.py
cernest_probability/Gaussiandistribution.py
cernest_probability/Generaldistribution.py
cernest_probability/__init__.py
cernest_probability/test.py
cernest_probability.egg-info/PKG-INFO
cernest_probability.egg-info/SOURCES.txt
cernest_probability.egg-info/dependency_links.txt
cernest_probability.egg-info/not-zip-safe
cernest_probability.egg-info/top_level.txt