Metadata-Version: 2.1
Name: cernest-probability
Version: 0.1
Summary: Gaussian and Binomial distributions
Home-page: UNKNOWN
Author: Ernest Chukwunta
Author-email: ernestchukwunta@yahoo.com
License: UNKNOWN
Platform: UNKNOWN
